probability_chain/__init__.py
probability_chain/core.py
probability_chain-0.2.0.dist-info/licenses/LICENSE
probability_chain-0.2.0.dist-info/METADATA
probability_chain-0.2.0.dist-info/WHEEL
probability_chain-0.2.0.dist-info/top_level.txt
probability_chain-0.2.0.dist-info/RECORD
